{"namedChunkGroups":{"polyfill":{"name":"polyfill","assets":[{"name":"webpack-runtime-c6f914c2a47676276409.js","size":4885},{"name":"polyfill-62884d650ea5c675a6d1.js","size":82584}],"filteredAssets":0,"assetsSize":87469,"filteredAuxiliaryAssets":2,"auxiliaryAssetsSize":221473},"app":{"name":"app","assets":[{"name":"webpack-runtime-c6f914c2a47676276409.js","size":4885},{"name":"framework-9931dd61ac6c47cb5ad1.js","size":128957},{"name":"app-8faf8fec27f01ed81a59.js","size":77583}],"filteredAssets":0,"assetsSize":211425,"filteredAuxiliaryAssets":3,"auxiliaryAssetsSize":686249},"component---src-pages-404-js":{"name":"component---src-pages-404-js","assets":[{"name":"component---src-pages-404-js-18d1725fba7b06c5e042.js","size":806}],"filteredAssets":0,"assetsSize":806,"filteredAuxiliaryAssets":1,"auxiliaryAssetsSize":1992},"component---src-pages-doc-js":{"name":"component---src-pages-doc-js","assets":[{"name":"component---src-pages-doc-js-fbd4d3983e227f8ac805.js","size":4544}],"filteredAssets":0,"assetsSize":4544,"filteredAuxiliaryAssets":1,"auxiliaryAssetsSize":7982},"component---src-pages-index-tsx":{"name":"component---src-pages-index-tsx","assets":[{"name":"styles.d0de4a6e86ba1170c07f.css","size":124761},{"name":"component---src-pages-index-tsx-71e2184ea73774356dc5.js","size":89220}],"filteredAssets":0,"assetsSize":213981,"filteredAuxiliaryAssets":20,"auxiliaryAssetsSize":842106}},"assetsByChunkName":{"polyfill":["webpack-runtime-c6f914c2a47676276409.js","polyfill-62884d650ea5c675a6d1.js"],"app":["webpack-runtime-c6f914c2a47676276409.js","framework-9931dd61ac6c47cb5ad1.js","app-8faf8fec27f01ed81a59.js"],"component---src-pages-404-js":["component---src-pages-404-js-18d1725fba7b06c5e042.js"],"component---src-pages-doc-js":["component---src-pages-doc-js-fbd4d3983e227f8ac805.js"],"component---src-pages-index-tsx":["styles.d0de4a6e86ba1170c07f.css","component---src-pages-index-tsx-71e2184ea73774356dc5.js"]},"childAssetsByChunkName":{}}